8bit Comparator/comparator.v
module comparator(a,b,gt,lt,eq);
input [7:0] a,b;
output reg gt,lt,eq;

integer i;
always @(a or b) begin : COMP
  gt=0; lt=0; eq=1;
  for(i = 7;i>=0;i=i-1) begin
    if(a[i] > b[i]) begin 
      gt=1; lt=0; eq=0; 
      disable COMP; 
      end
    else if(a[i] < b[i]) begin 
      gt=0; lt=1; eq=0; 
      disable COMP;
      end
  end
end
endmodule

8bit Comparator/comparator_tb.v
`include "comparator.v"

module comparator_tb;
reg [7:0] a,b;
wire gt,lt,eq;

comparator c1(a,b,gt,lt,eq);

initial begin
a = 8'b00000000; b = 8'b00000000; #10;
a = 8'b00000001; b = 8'b00000000; #10;
a = 8'b00000000; b = 8'b00000001; #10;
a = 8'b00000011; b = 8'b00000001; #10;
a = 8'b00000001; b = 8'b00000011; #10;
a = 8'b11111111; b = 8'b00000000; #10;
a = 8'b00000000; b = 8'b11111111; #10;
a = 8'b10101010; b = 8'b01010101; #10;
a = 8'b01010101; b = 8'b10101010; #10;
end

initial begin
$monitor("a=%b b=%b gt=%b lt=%b eq=%b",a,b,gt,lt,eq);
$dumpfile("comparator_wave.vcd");
$dumpvars(0,comparator_tb);
end
endmodule

8bit Comparator/comparator_wave.vcd
$date
	Sat Feb 21 16:35:32 2026
$end
$version
	Icarus Verilog
$end
$timescale
	1s
$end
$scope module comparator_tb $end
$var wire 1 ! lt $end
$var wire 1 " gt $end
$var wire 1 # eq $end
$var reg 8 $ a [7:0] $end
$var reg 8 % b [7:0] $end
$scope module c1 $end
$var wire 8 & a [7:0] $end
$var wire 8 ' b [7:0] $end
$var reg 1 # eq $end
$var reg 1 " gt $end
$var reg 1 ! lt $end
$var integer 32 ( i [31:0] $end
$scope begin COMP $end
$upscope $end
$upscope $end
$upscope $end
$enddefinitions $end
$comment Show the parameter values. $end
$dumpall
$end
#0
$dumpvars
b11111111111111111111111111111111 (
b0 '
b0 &
b0 %
b0 $
1#
0"
0!
$end
#10
0#
1"
b0 (
b1 $
b1 &
#20
1!
b0 (
0#
0"
b1 %
b1 '
b0 $
b0 &
#30
1"
b1 (
0#
0!
b11 $
b11 &
#40
1!
b1 (
0#
0"
b11 %
b11 '
b1 $
b1 &
#50
1"
b111 (
0#
0!
b0 %
b0 '
b11111111 $
b11111111 &
#60
1!
0#
0"
b11111111 %
b11111111 '
b0 $
b0 &
#70
1"
0#
0!
b1010101 %
b1010101 '
b10101010 $
b10101010 &
#80
1!
0#
0"
b10101010 %
b10101010 '
b1010101 $
b1010101 &
