qn8/decoder3_8.v
module decoder3_8(I,Y);
input[2:0] I;
output[7:0] Y;

and a1(Y[0],~I[2],~I[1],~I[0]);
and a2(Y[1],~I[2],~I[1],I[0]);
and a3(Y[2],~I[2],I[1],~I[0]);
and a4(Y[3],~I[2],I[1],I[0]);
and a5(Y[4],I[2],~I[1],~I[0]);
and a6(Y[5],I[2],~I[1],I[0]);
and a7(Y[6],I[2],I[1],~I[0]);
and a8(Y[7],I[2],I[1],I[0]);

endmodule

qn8/decoder_tb.v
module decoder_tb;
reg[2:0] I;
wire[7:0] Y;

decoder3_8 DUT(I,Y);

initial
begin
  $dumpfile("decoder.vcd");
  $dumpvars(0,decoder_tb);
  $monitor($time," Input = %b | Output = %b",I,Y);
  I = 3'd7;
  #10 I=3'd6;
  #10 I=3'd5;
  #10 I=3'd4;
  #10 I=3'd3;
  #10 I=3'd2;
  #10 I=3'd1;
  #10 I=3'd0;
  #10 $finish;
end
endmodule

qn8/decoder.vcd
$date
	Thu Jan 22 23:46:59 2026
$end
$version
	Icarus Verilog
$end
$timescale
	1s
$end
$scope module decoder_tb $end
$var wire 8 ! Y [7:0] $end
$var reg 3 " I [2:0] $end
$scope module DUT $end
$var wire 3 # I [2:0] $end
$var wire 8 $ Y [7:0] $end
$upscope $end
$upscope $end
$enddefinitions $end
$comment Show the parameter values. $end
$dumpall
$end
#0
$dumpvars
b10000000 $
b111 #
b111 "
b10000000 !
$end
#10
b1000000 !
b1000000 $
b110 "
b110 #
#20
b100000 !
b100000 $
b101 "
b101 #
#30
b10000 !
b10000 $
b100 "
b100 #
#40
b1000 !
b1000 $
b11 "
b11 #
#50
b100 !
b100 $
b10 "
b10 #
#60
b10 !
b10 $
b1 "
b1 #
#70
b1 !
b1 $
b0 "
b0 #
